{
  "data": {
    "article": {},
    "attachments": {},
    "author_id": "1343151486432399360",
    "conversation_id": "2072247254350713043",
    "created_at": "2026-07-01T10:29:21.000Z",
    "edit_controls": {
      "editable_until": "2026-07-01T11:29:21.000Z",
      "edits_remaining": 5,
      "is_edit_eligible": false
    },
    "edit_history_tweet_ids": [
      "2072266301641281911"
    ],
    "entities": {
      "mentions": [
        {
          "end": 12,
          "id": "1320354023451496450",
          "start": 0,
          "username": "OuO02213882"
        },
        {
          "end": 26,
          "id": "1519649212736049152",
          "start": 13,
          "username": "Mark67358226"
        }
      ]
    },
    "geo": {},
    "id": "2072266301641281911",
    "in_reply_to_user_id": "1320354023451496450",
    "lang": "zh",
    "note_tweet": {
      "entities": {}
    },
    "possibly_sensitive": false,
    "public_metrics": {
      "bookmark_count": 0,
      "impression_count": 0,
      "like_count": 0,
      "quote_count": 0,
      "reply_count": 0,
      "retweet_count": 0
    },
    "referenced_tweets": [
      {
        "id": "2072264477807104250",
        "type": "replied_to"
      }
    ],
    "reply_settings": "everyone",
    "text": "@OuO02213882 @Mark67358226 什么什么？！感谢大佬！！！"
  },
  "includes": {
    "tweets": [
      {
        "article": {},
        "attachments": {},
        "author_id": "1343151486432399360",
        "conversation_id": "2072247254350713043",
        "created_at": "2026-07-01T10:29:21.000Z",
        "edit_controls": {
          "editable_until": "2026-07-01T11:29:21.000Z",
          "edits_remaining": 5,
          "is_edit_eligible": false
        },
        "edit_history_tweet_ids": [
          "2072266301641281911"
        ],
        "entities": {
          "mentions": [
            {
              "end": 12,
              "id": "1320354023451496450",
              "start": 0,
              "username": "OuO02213882"
            },
            {
              "end": 26,
              "id": "1519649212736049152",
              "start": 13,
              "username": "Mark67358226"
            }
          ]
        },
        "geo": {},
        "id": "2072266301641281911",
        "in_reply_to_user_id": "1320354023451496450",
        "lang": "zh",
        "note_tweet": {
          "entities": {}
        },
        "possibly_sensitive": false,
        "public_metrics": {
          "bookmark_count": 0,
          "impression_count": 0,
          "like_count": 0,
          "quote_count": 0,
          "reply_count": 0,
          "retweet_count": 0
        },
        "referenced_tweets": [
          {
            "id": "2072264477807104250",
            "type": "replied_to"
          }
        ],
        "reply_settings": "everyone",
        "text": "@OuO02213882 @Mark67358226 什么什么？！感谢大佬！！！"
      },
      {
        "article": {},
        "attachments": {},
        "author_id": "1320354023451496450",
        "conversation_id": "2072247254350713043",
        "created_at": "2026-07-01T10:22:06.000Z",
        "edit_controls": {
          "editable_until": "2026-07-01T11:22:06.000Z",
          "edits_remaining": 5,
          "is_edit_eligible": false
        },
        "edit_history_tweet_ids": [
          "2072264477807104250"
        ],
        "entities": {
          "mentions": [
            {
              "end": 12,
              "id": "1343151486432399360",
              "start": 0,
              "username": "StarryNocts"
            },
            {
              "end": 26,
              "id": "1519649212736049152",
              "start": 13,
              "username": "Mark67358226"
            }
          ]
        },
        "geo": {},
        "id": "2072264477807104250",
        "in_reply_to_user_id": "1343151486432399360",
        "lang": "ja",
        "note_tweet": {
          "entities": {}
        },
        "possibly_sensitive": false,
        "public_metrics": {
          "bookmark_count": 0,
          "impression_count": 13,
          "like_count": 1,
          "quote_count": 0,
          "reply_count": 1,
          "retweet_count": 0
        },
        "referenced_tweets": [
          {
            "id": "2072257746091573469",
            "type": "replied_to"
          }
        ],
        "reply_settings": "everyone",
        "text": "@StarryNocts @Mark67358226 羨慕啥喵"
      }
    ],
    "users": [
      {
        "created_at": "2020-12-27T11:07:31.000Z",
        "description": "07｜mtx🏳‍⚧｜femboy｜死肥宅｜无糖｜清水｜社恐不线下｜社会学｜焦虑玉玉中｜备用:@StarryNoct ｜老公:@chinyu_ouo \n对不起对不起对不起我的错 无人在意 互fo请私信（",
        "entities": {
          "description": {
            "mentions": [
              {
                "end": 57,
                "start": 46,
                "username": "StarryNoct"
              },
              {
                "end": 73,
                "start": 62,
                "username": "chinyu_ouo"
              }
            ]
          }
        },
        "id": "1343151486432399360",
        "name": "​碎星笨笨✨",
        "pinned_tweet_id": "2037145943125221540",
        "profile_image_url": "https://pbs.twimg.com/profile_images/2070068207461998592/snBVwnOw_normal.jpg",
        "protected": false,
        "public_metrics": {
          "followers_count": 1496,
          "following_count": 794,
          "like_count": 4154,
          "listed_count": 4,
          "media_count": 253,
          "tweet_count": 8309
        },
        "url": "",
        "username": "StarryNocts",
        "verified": true
      },
      {
        "created_at": "2020-10-25T13:18:36.000Z",
        "description": "還在慢慢認識自己喵",
        "id": "1320354023451496450",
        "location": "不能說喵 反正不在杭州喵",
        "name": "粉天藍貓OuO",
        "profile_image_url": "https://pbs.twimg.com/profile_images/2057350986352734208/QXkn4_0I_normal.jpg",
        "protected": false,
        "public_metrics": {
          "followers_count": 589,
          "following_count": 1177,
          "like_count": 25005,
          "listed_count": 1,
          "media_count": 48,
          "tweet_count": 344
        },
        "url": "",
        "username": "OuO02213882",
        "verified": true
      },
      {
        "created_at": "2022-04-28T12:06:42.000Z",
        "description": "生產日期：2010.9.6 | 181cm 57kg | 北京昌平🇨🇳 | 主要繁體🇹🇼 簡體🉑 | 是男孩子w |日語🇯🇵 朝鮮語🇰🇷也會一點 | 友跨+LGBT友好 | 留長髮中 | 喜歡漢服、東亞文化和可愛的男孩子（小南梁），歡迎諸君找我聊天口牙！（求你們私信找我聊天吧！）僅交友不約！",
        "entities": {
          "url": {
            "urls": [
              {
                "display_url": "dreamail.cn/send?dm=2225cc…",
                "end": 23,
                "expanded_url": "https://dreamail.cn/send?dm=2225ccc1-e4e4-4a1f-98a3-24d13a1d0999",
                "start": 0,
                "url": "https://t.co/0zMrtG63tc"
              }
            ]
          }
        },
        "id": "1519649212736049152",
        "location": "琉球國首里城",
        "name": "Lhn002",
        "pinned_tweet_id": "2070101728381591818",
        "profile_image_url": "https://pbs.twimg.com/profile_images/2020892688674103296/MTlilAxM_normal.jpg",
        "protected": false,
        "public_metrics": {
          "followers_count": 1077,
          "following_count": 1431,
          "like_count": 24114,
          "listed_count": 3,
          "media_count": 274,
          "tweet_count": 5358
        },
        "url": "https://t.co/0zMrtG63tc",
        "username": "Mark67358226",
        "verified": true
      }
    ]
  }
}