{
  "data": {
    "article": {},
    "attachments": {},
    "author_id": "1343151486432399360",
    "conversation_id": "2040952076508025215",
    "created_at": "2026-04-06T00:37:48.000Z",
    "edit_controls": {
      "editable_until": "2026-04-06T01:37:48.000Z",
      "edits_remaining": 5,
      "is_edit_eligible": true
    },
    "edit_history_tweet_ids": [
      "2040952076508025215"
    ],
    "entities": {},
    "geo": {},
    "id": "2040952076508025215",
    "lang": "zh",
    "note_tweet": {
      "entities": {}
    },
    "possibly_sensitive": false,
    "public_metrics": {
      "bookmark_count": 0,
      "impression_count": 0,
      "like_count": 0,
      "quote_count": 0,
      "reply_count": 0,
      "retweet_count": 0
    },
    "reply_settings": "everyone",
    "text": "今天没吃帕罗西汀 感觉好舒服😋"
  },
  "includes": {
    "tweets": [
      {
        "article": {},
        "attachments": {},
        "author_id": "1343151486432399360",
        "conversation_id": "2040952076508025215",
        "created_at": "2026-04-06T00:37:48.000Z",
        "edit_controls": {
          "editable_until": "2026-04-06T01:37:48.000Z",
          "edits_remaining": 5,
          "is_edit_eligible": true
        },
        "edit_history_tweet_ids": [
          "2040952076508025215"
        ],
        "entities": {},
        "geo": {},
        "id": "2040952076508025215",
        "lang": "zh",
        "note_tweet": {
          "entities": {}
        },
        "possibly_sensitive": false,
        "public_metrics": {
          "bookmark_count": 0,
          "impression_count": 0,
          "like_count": 0,
          "quote_count": 0,
          "reply_count": 0,
          "retweet_count": 0
        },
        "reply_settings": "everyone",
        "text": "今天没吃帕罗西汀 感觉好舒服😋"
      }
    ],
    "users": [
      {
        "created_at": "2020-12-27T11:07:31.000Z",
        "description": "大傻福｜备用:@StarryNoct 小号:@WindyLuster\n对不起对不起对不起我的错 无人在意 凭感觉回fo（",
        "entities": {
          "description": {
            "mentions": [
              {
                "end": 18,
                "start": 7,
                "username": "StarryNoct"
              },
              {
                "end": 34,
                "start": 22,
                "username": "WindyLuster"
              }
            ]
          }
        },
        "id": "1343151486432399360",
        "location": "摸鱼中…",
        "name": "​碎星波波✨（傻福版）",
        "pinned_tweet_id": "2037145943125221540",
        "profile_image_url": "https://pbs.twimg.com/profile_images/2032817226680774656/ga377Pls_normal.jpg",
        "protected": false,
        "public_metrics": {
          "followers_count": 276,
          "following_count": 221,
          "like_count": 1687,
          "listed_count": 0,
          "media_count": 125,
          "tweet_count": 2702
        },
        "username": "StarryNocts",
        "verified": false
      }
    ]
  }
}